example_package_reyniel26/__init__.py
example_package_reyniel26/example.py
example_package_reyniel26/sample.txt
example_package_reyniel26-0.0.5.dist-info/LICENSE
example_package_reyniel26-0.0.5.dist-info/METADATA
example_package_reyniel26-0.0.5.dist-info/WHEEL
example_package_reyniel26-0.0.5.dist-info/top_level.txt
example_package_reyniel26-0.0.5.dist-info/RECORD
