Metadata-Version: 2.1
Name: example-package-reyniel26
Version: 0.0.5
Summary: A small example package
Author-email: Reyniel Mark Escamillas <some@email.com>
Project-URL: Homepage, https://github.com/reyniel26/packaging_playground
Project-URL: Bug Tracker, https://github.com/reyniel26/packaging_playground/issues
Classifier: Programming Language :: Python :: 3
Classifier: License :: OSI Approved :: MIT License
Classifier: Operating System :: OS Independent
Requires-Python: >=3.7
License-File: LICENSE
Requires-Dist: pylint (>=2.15.6)
Requires-Dist: flake8 (>=5.0.4)
Provides-Extra: tests
Requires-Dist: pytest (>=7.2.0) ; extra == 'tests'
Requires-Dist: pylint (>=2.15.6) ; extra == 'tests'
Requires-Dist: flake8 (>=5.0.4) ; extra == 'tests'
